{
  "LOCATION AND TRANSPORATION (LT)": [
    {
      "name": "Sensitive Land Protection",
      "type": "Credit",
      "points": 1
    },
    {
      "name": "High-Priority Site",
      "type": "Credit",
      "points": 2
    },
    {
      "name": "Surrounding Density and Diverse Uses",
      "type": "Credit",
      "points": 5
    },
    {
      "name": "Access to Quality Transit",
      "type": "Credit",
      "points": 5
    },
    {
      "name": "Bicycle Facilities",
      "type": "Credit",
      "points": 1
    },
    {
      "name": "Reduced Parking Footprint",
      "type": "Credit",
      "points": 1
    },
    {
      "name": "Green Vehicles",
      "type": "Credit",
      "points": 1
    },
    {
      "name": "Construction Activity Pollution Prevention",
      "type": "Credit",
      "points": 0
    },
    {
      "name": "Site Assessment",
      "type": "Credit",
      "points": 1
    },
    {
      "name": "Site Development—Protect or Restore Habitat",
      "type": "Credit",
      "points": 2
    },
    {
      "name": "Open Space",
      "type": "Credit",
      "points": 1
    },
    {
      "name": "Rainwater Management",
      "type": "Credit",
      "points": 3
    },
    {
      "name": "Heat Island Reduction",
      "type": "Credit",
      "points": 2
    },
    {
      "name": "Light Pollution Reduction",
      "type": "Credit",
      "points": 1
    }
  ],
  "WATER EFFICIENCY (WE)": [
    {
      "name": "Outdoor Water Use Reduction",
      "type": "Prerequisite",
      "points": 0
    },
    {
      "name": "Indoor Water Use Reduction",
      "type": "Prerequisite",
      "points": 0
    },
    {
      "name": "Building-Level Water Metering",
      "type": "Prerequisite",
      "points": 0
    },
    {
      "name": "Outdoor Water Use Reduction",
      "type": "Credit",
      "points": 2
    },
    {
      "name": "Indoor Water Use Reduction",
      "type": "Credit",
      "points": 6
    },
    {
      "name": "Cooling Tower Water Use",
      "type": "Credit",
      "points": 2
    },
    {
      "name": "Water Metering",
      "type": "Credit",
      "points": 1
    }
  ],


  "ENERGY AND ATMOSPHERE": [
    {
      "name": "Fundamental Commissioning and Verification",
      "type": "Prerequisite",
      "points": 0
    },
    {
      "name": "Minimum Energy Performance",
      "type": "Prerequisite",
      "points": 0
    },
    {
      "name": "Building-Level Energy Metering",
      "type": "Prerequisite",
      "points": 0
    },
    {
      "name": "Fundamental Refrigerant Management",
      "type": "Prerequisite",
      "points": 0
    },
    {
      "name": "Enhanced Commissioning",
      "type": "Credit",
      "points": 6
    },
    {
      "name": "Optimize Energy Performance",
      "type": "Credit",
      "points": 18
    },
    {
      "name": "Advanced Energy Metering",
      "type": "Credit",
      "points": 1
    },
    {
      "name": "Demand Response",
      "type": "Credit",
      "points": 2
    },
    {
      "name": "Renewable Energy Production",
      "type": "Credit",
      "points": 3
    },
    {
      "name": "Enhanced Refrigerant Management",
      "type": "Credit",
      "points": 1
    },
    {
      "name": "Green Power and Carbon Offsets",
      "type": "Credit",
      "points": 2
    }
  ],


  "MATERIALS AND RESOURCES (MR)": [
    {
      "name": "Storage and Collection of Recyclables",
      "type": "Prerequisite",
      "points": 0
    },
    {
      "name": "Construction and Demolition Waste Management Planning",
      "type": "Prerequisite",
      "points": 0
    },
    {
      "name": "Building Life-Cycle Impact Reduction",
      "type": "Credit",
      "points": 5
    },
    {
      "name": "Building Product Disclosure and Optimization—Environmental Product Declarations",
      "type": "Credit",
      "points": 2
    },
    {
      "name": "Building Product Disclosure and Optimization—Sourcing of Raw Materials",
      "type": "Credit",
      "points": 2
    },
    
    {
      "name": "Building Product Disclosure and Optimization—Material Ingredients",
      "type": "Credit",
      "points": 2
    },
    {
      "name": "Construction and Demolition Waste Management",
      "type": "Credit",
      "points": 2
    }
  ],  


  "INDOOR ENVIRONMENTAL QUALITY (EQ)": [
    {
      "name": "Minimum Indoor Air Quality Performance",
      "type": "Prerequisite",
      "points": 0
    },
    {
      "name": "Environmental Tobacco Smoke Control",
      "type": "Prerequisite",
      "points": 0
    },
    {
      "name": "Enhanced Indoor Air Quality Strategies",
      "type": "Credit",
      "points": 2
    },
    {
      "name": "Low-Emitting Materials",
      "type": "Credit",
      "points": 3
    },
    {
      "name": "Construction Indoor Air Quality Management Plan",
      "type": "Credit",
      "points": 1
    },
    {
      "name": "Indoor Air Quality Assessment",
      "type": "Credit",
      "points": 2
    },
    {
      "name": "Thermal Comfort",
      "type": "Credit",
      "points": 1
    },
    {
      "name": "Interior Lighting",
      "type": "Credit",
      "points": 2
    },
    {
      "name": "Daylight",
      "type": "Credit",
      "points": 3
    },
    {
      "name": "Quality Views",
      "type": "Credit",
      "points": 1
    },
    {
      "name": "Acoustic Performance",
      "type": "Credit",
      "points": 1
    }
  ],


  "Innovation (IN)": [
    {
      "name": "Innovation",
      "type": "Credit",
      "points": 5
    },
    {
      "name": "LEED Accredited Professional",
      "type": "Credit",
      "points": 1
    }
  ],

  "Regional Priority (RP)": [
    {
      "name": "Regional Priority: Specific Credit",
      "type": "Credit",
      "points": 1
    },
    {
      "name": "Regional Priority: Specific Credit",
      "type": "Credit",
      "points": 1
    },
    {
      "name": "Regional Priority: Specific Credit",
      "type": "Credit",
      "points": 1
    },
    {
      "name": "Regional Priority: Specific Credit",
      "type": "Credit",
      "points": 1
    }
  ]
}
